Metadata-Version: 2.1
Name: lambda2color
Version: 0.7
Summary: This is a simple library to transform a given light wavelength into the corresponding RGB color.
Home-page: https://github.com/laurentperrinet/lambda2color
Download-URL: https://github.com/laurentperrinet/lambda2color/tarball/0.7
Author: Laurent Perrinet INT - CNRS
Author-email: Laurent.Perrinet@univ-amu.fr
License: GPLv2
Keywords: computational neuroscience,simulation,analysis,visualization,biologically-inspired,computer vision
Classifier: Development Status :: 3 - Alpha
Classifier: Environment :: Console
Classifier: License :: OSI Approved :: GNU General Public License (GPL)
Classifier: Operating System :: POSIX
Classifier: Topic :: Scientific/Engineering
Classifier: Topic :: Utilities
Classifier: Programming Language :: Python :: 3
Classifier: Programming Language :: Python :: 3.10
Provides-Extra: html
License-File: LICENSE.md
